LICENSE.pdf
MANIFEST.in
README.md
setup.py
OASYS1_ShadowOui_Advanced_Tools.egg-info/PKG-INFO
OASYS1_ShadowOui_Advanced_Tools.egg-info/SOURCES.txt
OASYS1_ShadowOui_Advanced_Tools.egg-info/dependency_links.txt
OASYS1_ShadowOui_Advanced_Tools.egg-info/entry_points.txt
OASYS1_ShadowOui_Advanced_Tools.egg-info/namespace_packages.txt
OASYS1_ShadowOui_Advanced_Tools.egg-info/not-zip-safe
OASYS1_ShadowOui_Advanced_Tools.egg-info/requires.txt
OASYS1_ShadowOui_Advanced_Tools.egg-info/top_level.txt
orangecontrib/__init__.py
orangecontrib/shadow_advanced_tools/__init__.py
orangecontrib/shadow_advanced_tools/menu/__init__.py
orangecontrib/shadow_advanced_tools/menu/ow_shadow_advanced_tools_menu.py
orangecontrib/shadow_advanced_tools/util/__init__.py
orangecontrib/shadow_advanced_tools/util/gui.py
orangecontrib/shadow_advanced_tools/widgets/__init__.py
orangecontrib/shadow_advanced_tools/widgets/optical_elements/__init__.py
orangecontrib/shadow_advanced_tools/widgets/optical_elements/ow_bendable_ellipsoid_mirror.py
orangecontrib/shadow_advanced_tools/widgets/optical_elements/ow_double_rod_bendable_ellipsoid_mirror.py
orangecontrib/shadow_advanced_tools/widgets/optical_elements/ow_fresnel_zone_plate.py
orangecontrib/shadow_advanced_tools/widgets/optical_elements/bl/__init__.py
orangecontrib/shadow_advanced_tools/widgets/optical_elements/bl/fixed_rods_bender_ellispoid_mirror_bl.py
orangecontrib/shadow_advanced_tools/widgets/optical_elements/bl/flexural_hinge_bender_ellipsoid_mirror_bl.py
orangecontrib/shadow_advanced_tools/widgets/optical_elements/bl/fresnel_zone_plate.py
orangecontrib/shadow_advanced_tools/widgets/optical_elements/icons/bendable_ellipsoid_mirror.png
orangecontrib/shadow_advanced_tools/widgets/optical_elements/icons/double_rod_bendable_ellipsoid_mirror.png
orangecontrib/shadow_advanced_tools/widgets/optical_elements/icons/oe.png
orangecontrib/shadow_advanced_tools/widgets/optical_elements/icons/zone_plate.png
orangecontrib/shadow_advanced_tools/widgets/sources/__init__.py
orangecontrib/shadow_advanced_tools/widgets/sources/ow_hybrid_undulator.py
orangecontrib/shadow_advanced_tools/widgets/sources/attributes/__init__.py
orangecontrib/shadow_advanced_tools/widgets/sources/attributes/hybrid_undulator_attributes.py
orangecontrib/shadow_advanced_tools/widgets/sources/bl/__init__.py
orangecontrib/shadow_advanced_tools/widgets/sources/bl/hybrid_undulator_bl.py
