Metadata-Version: 2.1
Name: OASYS1-ShadowOui-Advanced-Tools
Version: 1.0.136
Summary: ShadowOui advanced simulation tools
Home-page: https://github.com/oasys-kit/ShadowOui-Advanced-Tools
Download-URL: https://github.com/oasys-kit/ShadowOui-Advanced-Tools
Author: Luca Rebuffi
Author-email: lrebuffi@anl.gov
License: GPLv3
Keywords: raytracing,simulator,oasys1
Classifier: Development Status :: 5 - Production/Stable
Classifier: Environment :: X11 Applications :: Qt
Classifier: Environment :: Console
Classifier: Environment :: Plugins
Classifier: Programming Language :: Python :: 3
Classifier: Intended Audience :: Science/Research
License-File: LICENSE.pdf
Requires-Dist: setuptools
Requires-Dist: oasys1>=1.2.131
Requires-Dist: syned-gui>=1.0.2
Requires-Dist: scikit-image
Requires-Dist: oasys-srwpy>=1.0.5
Requires-Dist: shadow-hybrid-methods>=1.0.7
Requires-Dist: OASYS1-ShadowOui>=1.5.201
